Workbook

Sheet Ringkasan
A1: Rancangan Fitur Marketplace UMKM — Gap Analysis Repository myumkm
A2: Status dihitung otomatis dari sheet "Daftar Fitur" (kolom E). Ubah status di sana, ringkasan ikut berubah.
A4: Kelompok Pengguna | B4: Total Fitur | C4: ✅ Ada | D4: ❌ Belum | E4: % Selesai | F4: ⭐ Pembeda | G4: ⭐ Pembeda yang Belum Ada | H4: 🧓 Low-tech
A5: Pembeli | B5: =COUNTIF('Daftar Fitur'!$B$2:$B$101,A5) -> 37 | C5: =COUNTIFS('Daftar Fitur'!$B$2:$B$101,A5,'Daftar Fitur'!$E$2:$E$101,"Ada") -> 22 | D5: =COUNTIFS('Daftar Fitur'!$B$2:$B$101,A5,'Daftar Fitur'!$E$2:$E$101,"Belum") -> 15 | E5: =IF(B5=0,0,C5/B5) -> 0.59459459 | F5: =COUNTIFS('Daftar Fitur'!$B$2:$B$101,A5,'Daftar Fitur'!$F$2:$F$101,"Ya") -> 5 | G5: =COUNTIFS('Daftar Fitur'!$B$2:$B$101,A5,'Daftar Fitur'!$F$2:$F$101,"Ya",'Daftar Fitur'!$E$2:$E$101,"Belum") -> 4 | H5: =COUNTIFS('Daftar Fitur'!$B$2:$B$101,A5,'Daftar Fitur'!$G$2:$G$101,"Ya") -> 9
A6: Penjual / Pelaku UMKM | B6: =COUNTIF('Daftar Fitur'!$B$2:$B$101,A6) -> 41 | C6: =COUNTIFS('Daftar Fitur'!$B$2:$B$101,A6,'Daftar Fitur'!$E$2:$E$101,"Ada") -> 21 | D6: =COUNTIFS('Daftar Fitur'!$B$2:$B$101,A6,'Daftar Fitur'!$E$2:$E$101,"Belum") -> 20 | E6: =IF(B6=0,0,C6/B6) -> 0.51219512 | F6: =COUNTIFS('Daftar Fitur'!$B$2:$B$101,A6,'Daftar Fitur'!$F$2:$F$101,"Ya") -> 10 | G6: =COUNTIFS('Daftar Fitur'!$B$2:$B$101,A6,'Daftar Fitur'!$F$2:$F$101,"Ya",'Daftar Fitur'!$E$2:$E$101,"Belum") -> 8 | H6: =COUNTIFS('Daftar Fitur'!$B$2:$B$101,A6,'Daftar Fitur'!$G$2:$G$101,"Ya") -> 8
A7: Admin / Pengelola Platform | B7: =COUNTIF('Daftar Fitur'!$B$2:$B$101,A7) -> 22 | C7: =COUNTIFS('Daftar Fitur'!$B$2:$B$101,A7,'Daftar Fitur'!$E$2:$E$101,"Ada") -> 9 | D7: =COUNTIFS('Daftar Fitur'!$B$2:$B$101,A7,'Daftar Fitur'!$E$2:$E$101,"Belum") -> 13 | E7: =IF(B7=0,0,C7/B7) -> 0.40909091 | F7: =COUNTIFS('Daftar Fitur'!$B$2:$B$101,A7,'Daftar Fitur'!$F$2:$F$101,"Ya") -> 2 | G7: =COUNTIFS('Daftar Fitur'!$B$2:$B$101,A7,'Daftar Fitur'!$F$2:$F$101,"Ya",'Daftar Fitur'!$E$2:$E$101,"Belum") -> 2 | H7: =COUNTIFS('Daftar Fitur'!$B$2:$B$101,A7,'Daftar Fitur'!$G$2:$G$101,"Ya") -> 0
A8: TOTAL | B8: =SUM(B5:B7) -> 100 | C8: =SUM(C5:C7) -> 52 | D8: =SUM(D5:D7) -> 48 | E8: =IF(B8=0,0,C8/B8) -> 0.52 | F8: =SUM(F5:F7) -> 17 | G8: =SUM(G5:G7) -> 14 | H8: =SUM(H5:H7) -> 17
A10: Keterangan
A11: Ada | B11: Fitur inti sudah ada di kode repo (catatan menjelaskan batasan bila sebagian).
A12: Belum | B12: Fitur belum ada di repo.
A13: ⭐ Pembeda | B13: Fitur yang membedakan dari marketplace besar.
A14: 🧓 Low-tech | B14: Dirancang ramah UMKM/pengguna gagap teknologi.
A15: Kolom Prioritas | B15: Sel kuning di "Daftar Fitur" kolom K: diisi tim (dropdown P1–P4).
A16: Sumber | B16: Analisis kode repo xaralien/myumkm (CodeIgniter 3), per 13 Okt 2026. Dibaca dari kode, aplikasi tidak dijalankan.

Sheet Daftar Fitur
A1: No | B1: Kelompok Pengguna | C1: Sub-kategori | D1: Fitur | E1: Status di Repo | F1: Pembeda (⭐) | G1: Low-tech Friendly (🧓) | H1: Pain Point | I1: Fungsi Utama | J1: Bukti di Repo / Catatan | K1: Prioritas
A2: 1 | B2: Pembeli | C2: Akun & Akses | D2: Daftar & masuk akun | E2: Ada | H2: Pembeli perlu riwayat pesanan tersimpan | I2: Registrasi dengan nama, email, nomor WhatsApp. | J2: Auth.php
A3: 2 | B3: Pembeli | C3: Akun & Akses | D3: Belanja tanpa akun (guest checkout) | E3: Ada | G3: Ya | H3: Pembeli lokal malas daftar hanya untuk sekali beli | I3: Checkout cukup nama + nomor WA; pesanan dibuka lewat token. | J3: orders.user_id boleh NULL, Checkout::done/{token}
A4: 3 | B4: Pembeli | C4: Akun & Akses | D4: Lacak pesanan dengan nomor pesanan + nomor WA | E4: Ada | G4: Ya | H4: Pembeli tamu tidak punya akun untuk mengecek status | I4: Form lacak sederhana tanpa login. | J4: Track.php
A5: 4 | B5: Pembeli | C5: Akun & Akses | D5: Login OTP WhatsApp / tanpa kata sandi | E5: Belum | G5: Ya | H5: Pembeli sering lupa sandi | I5: Masuk cukup dengan kode OTP dikirim ke WA.
A6: 5 | B6: Pembeli | C6: Akun & Akses | D6: Lupa kata sandi mandiri | E6: Belum | H6: Saat ini reset sandi harus lewat admin | I6: Tautan/OTP reset sandi sendiri. | J6: Repo hanya punya reset oleh admin: admin/Users::sandi
A7: 6 | B7: Pembeli | C7: Akun & Akses | D7: Profil & ubah sandi | E7: Ada | H7: Data kontak berubah | I7: Ubah nama, foto, nomor, sandi. | J7: Akun::profil
A8: 7 | B8: Pembeli | C8: Penemuan Produk | D8: Katalog berbasis lokasi ("dekat saya") | E8: Ada | F8: Ya | H8: Pembeli ingin produk UMKM tetangga, ongkir murah & cepat | I8: Pilih kecamatan atau titik GPS, urutan produk mendahulukan toko terdekat. | J8: Location.php, Product_model::proximity_sql, toko_sekitar
A9: 8 | B9: Pembeli | C9: Penemuan Produk | D9: Pencarian & filter | E9: Ada | H9: Sulit menemukan produk spesifik | I9: Cari kata kunci, filter kategori & rentang harga. | J9: Shop.php, Product_model::build_filter, price_range
A10: 9 | B10: Pembeli | C10: Penemuan Produk | D10: Urutkan hasil | E10: Ada | H10: Ingin yang termurah/terbaik dulu | I10: Terbaru, ulasan terbaik, harga, nama. | J10: Product_model::sort_options
A11: 10 | B11: Pembeli | C11: Penemuan Produk | D11: Kategori UMKM dengan ikon | E11: Ada | H11: Pengguna awam lebih cepat mengenali gambar daripada teks | I11: Kartu kategori berikon di beranda. | J11: 15_kategori_umkm.sql
A12: 11 | B12: Pembeli | C12: Penemuan Produk | D12: Halaman toko | E12: Ada | H12: Pembeli ingin melihat reputasi & produk lain penjual | I12: Profil toko, nilai rata-rata, daftar produk. | J12: Toko.php, parts/toko_nilai.php
A13: 12 | B13: Pembeli | C13: Penemuan Produk | D13: Detail produk dengan varian & add-on | E13: Ada | H13: Produk UMKM sering punya ukuran/rasa/tambahan | I13: Pilih varian (dengan foto & selisih harga) dan add-on. | J13: Product_model::variants, addons_for_product
A14: 13 | B14: Pembeli | C14: Penemuan Produk | D14: Wishlist / simpan produk favorit | E14: Belum | H14: Pembeli ingin membeli nanti | I14: Tombol ♥ dan daftar favorit.
A15: 14 | B15: Pembeli | C15: Penemuan Produk | D15: Ikuti toko | E15: Belum | H15: Pelanggan setia tidak tahu kalau toko langganannya punya produk baru | I15: Follow toko + kabar produk baru.
A16: 15 | B16: Pembeli | C16: Penemuan Produk | D16: Rekomendasi & "terlaris" | E16: Belum | H16: Pembeli bingung memilih | I16: Rekomendasi berdasarkan riwayat, label terlaris di sekitar.
A17: 16 | B17: Pembeli | C17: Penemuan Produk | D17: Label "Produk Lokal / Halal / P-IRT / Buatan Tangan" | E17: Belum | F17: Ya | H17: Pembeli ingin yakin akan keamanan & keaslian produk UMKM | I17: Lencana terverifikasi di kartu produk.
A18: 17 | B18: Pembeli | C18: Penemuan Produk | D18: Bagikan produk ke WhatsApp | E18: Belum | G18: Ya | H18: Promosi UMKM paling efektif lewat grup WA | I18: Tombol share dengan pesan siap kirim. | J18: Ada kode tombol WA di v_produk.php tapi dikomentari
A19: 18 | B19: Pembeli | C19: Keranjang, Checkout & Pembayaran | D19: Keranjang & "Beli Langsung" | E19: Ada | H19: Ingin beli cepat satu barang | I19: Keranjang per toko dan jalur beli langsung. | J19: Cart.php, Cart_lib::mode_langsung
A20: 19 | B20: Pembeli | C20: Keranjang, Checkout & Pembayaran | D20: Buku alamat | E20: Ada | H20: Mengetik alamat berulang; penerima sering bukan pembeli | I20: Simpan banyak alamat ("Rumah", "Rumah Ibu"), pilih saat checkout. | J20: 22_buku_alamat.sql, Akun::alamat
A21: 20 | B21: Pembeli | C21: Keranjang, Checkout & Pembayaran | D21: Ongkir otomatis berdasarkan wilayah | E21: Ada | H21: Ongkir tidak jelas sebelum bayar | I21: Tarif kecamatan/kota/provinsi/luar provinsi dari toko, plus gratis ongkir minimal belanja. | J21: Cart_lib::shipping_fee
A22: 21 | B22: Pembeli | C22: Keranjang, Checkout & Pembayaran | D22: Pembayaran online (VA/QRIS/e-wallet via Duitku) | E22: Ada | H22: Transfer manual rawan salah & lama dicek | I22: Pembayaran terverifikasi otomatis via callback. | J22: Payment.php, libraries/Duitku.php
A23: 22 | B23: Pembeli | C23: Keranjang, Checkout & Pembayaran | D23: COD / bayar di tempat | E23: Belum | G23: Ya | H23: Banyak pembeli daerah belum percaya bayar di muka | I23: Opsi COD dengan batas nominal per toko. | J23: Ada sisa logika cod di Payment.php, tetapi Checkout::place selalu memakai Duitku
A24: 23 | B24: Pembeli | C24: Keranjang, Checkout & Pembayaran | D24: Voucher & promo | E24: Belum | H24: Pembeli mencari potongan harga | I24: Kode voucher toko/platform.
A25: 24 | B25: Pembeli | C25: Keranjang, Checkout & Pembayaran | D25: Checkout multi-toko | E25: Belum | F25: Ya | H25: Keranjang saat ini hanya untuk satu toko | I25: Beli dari beberapa toko dalam satu pembayaran.
A26: 25 | B26: Pembeli | C26: Keranjang, Checkout & Pembayaran | D26: Pre-order fleksibel (DP, tanggal ambil, kuota) | E26: Belum | F26: Ya | H26: Kue, katering, kerajinan dibuat berdasarkan pesanan | I26: Pilih tanggal kirim/ambil, bayar DP, kuota harian. | J26: Repo baru punya waktu_proses_hari di level toko
A27: 26 | B27: Pembeli | C27: Keranjang, Checkout & Pembayaran | D27: Ambil sendiri di toko (pickup) | E27: Belum | F27: Ya | H27: Tetangga satu kecamatan lebih suka mengambil sendiri | I27: Opsi ongkir 0 + jam ambil.
A28: 27 | B28: Pembeli | C28: Pasca-Pembelian | D28: Riwayat & status pesanan | E28: Ada | H28: Pembeli cemas menunggu | I28: Daftar pesanan dengan linimasa status & nomor resi. | J28: Akun::pesanan, Order_model::logs
A29: 28 | B29: Pembeli | C29: Pasca-Pembelian | D29: Batalkan pesanan dengan alasan | E29: Ada | H29: Salah pesan | I29: Pembatalan oleh pembeli, stok dikembalikan. | J29: Checkout::batal, Stok_lib::kembalikan
A30: 29 | B30: Pembeli | C30: Pasca-Pembelian | D30: Konfirmasi pesanan diterima | E30: Ada | H30: Dana penjual tertahan tanpa kepastian | I30: Tombol "Pesanan diterima". | J30: Checkout::terima
A31: 30 | B31: Pembeli | C31: Pasca-Pembelian | D31: Ajukan pengembalian dana (refund) | E31: Ada | H31: Barang tidak sesuai | I31: Form refund yang ditinjau penjual lalu diproses admin. | J31: Checkout::refund, Refund_model
A32: 31 | B32: Pembeli | C32: Pasca-Pembelian | D32: Ulasan dengan foto/video | E32: Ada | H32: Pembeli lain butuh bukti nyata | I32: Rating bintang + media, hanya dari pembeli asli, filter ulasan. | J32: Ulasan.php, 19_ulasan.sql
A33: 32 | B33: Pembeli | C33: Pasca-Pembelian | D33: Chat dengan toko (sebelum & sesudah beli) + lampiran | E33: Ada | H33: Ingin bertanya sebelum membeli tanpa pindah ke WA | I33: "Tanya ke toko" dan percakapan per pesanan. | J33: Chat.php, 18_tanya_toko.sql
A34: 33 | B34: Pembeli | C34: Pasca-Pembelian | D34: Notifikasi di dalam situs | E34: Ada | H34: Tidak tahu ada balasan/perubahan status | I34: Lonceng notifikasi & inbox. | J34: Akun::notif, inbox_json
A35: 34 | B35: Pembeli | C35: Pasca-Pembelian | D35: Notifikasi WhatsApp / email otomatis | E35: Belum | G35: Ya | H35: Pengguna jarang membuka web, tapi selalu membuka WA | I35: Kabar status pesanan dikirim ke WA.
A36: 35 | B36: Pembeli | C36: Pengalaman & Aksesibilitas | D36: Tampilan khusus HP otomatis | E36: Ada | G36: Ya | H36: Mayoritas pengguna UMKM memakai HP murah | I36: Deteksi perangkat & tampilan mobile terpisah, bisa ditukar manual. | J36: Tampilan_lib, views/mobile/
A37: 36 | B37: Pembeli | C37: Pengalaman & Aksesibilitas | D37: PWA / mode hemat kuota | E37: Belum | G37: Ya | H37: Sinyal lemah di daerah | I37: Bisa dipasang di layar utama, gambar ringan, cache offline.
A38: 37 | B38: Pembeli | C38: Pengalaman & Aksesibilitas | D38: Mode huruf besar & bahasa daerah | E38: Belum | G38: Ya | H38: Pengguna lansia/kurang terbiasa bahasa formal | I38: Pengaturan ukuran huruf, pilihan bahasa.
A39: 38 | B39: Penjual / Pelaku UMKM | C39: Onboarding & Profil Toko | D39: Buka toko langsung dari akun pembeli | E39: Ada | G39: Ya | H39: Pendaftaran penjual di marketplace besar panjang & membingungkan | I39: Satu akun = satu toko, form singkat. | J39: Akun::buka_toko
A40: 39 | B40: Penjual / Pelaku UMKM | C40: Onboarding & Profil Toko | D40: Profil toko dengan titik peta | E40: Ada | H40: Pembeli & kurir sulit menemukan lokasi | I40: Alamat, kecamatan, titik koordinat via peta (Leaflet/OSM). | J40: Seller::update_profile, valid_koordinat
A41: 40 | B41: Penjual / Pelaku UMKM | C41: Onboarding & Profil Toko | D41: Rekening pencairan | E41: Ada | H41: Penjual perlu tempat menerima uang | I41: Simpan bank, nomor, atas nama. | J41: Seller::rekening
A42: 41 | B42: Penjual / Pelaku UMKM | C42: Onboarding & Profil Toko | D42: Wizard onboarding bertahap + video panduan | E42: Belum | G42: Ya | H42: UMKM gaptek bingung harus mulai dari mana | I42: Checklist "Toko siap jualan" (foto profil → produk pertama → ongkir → rekening) dengan video 1 menit per langkah.
A43: 42 | B43: Penjual / Pelaku UMKM | C43: Onboarding & Profil Toko | D43: Bantuan legalitas (NIB, P-IRT, Halal) | E43: Belum | F43: Ya | H43: UMKM sulit naik kelas karena legalitas | I43: Panduan langkah-langkah, unggah dokumen, lencana terverifikasi di toko.
A44: 43 | B44: Penjual / Pelaku UMKM | C44: Onboarding & Profil Toko | D44: Mode libur / tutup sementara | E44: Belum | H44: Penjual pulang kampung, pesanan tetap masuk | I44: Toggle libur dengan tanggal buka kembali. | J44: Kini hanya admin yang dapat menonaktifkan toko
A45: 44 | B45: Penjual / Pelaku UMKM | C45: Manajemen Produk | D45: Tambah/ubah/aktifkan produk | E45: Ada | H45: Katalog perlu diperbarui cepat | I45: Form produk, toggle aktif/nonaktif. | J45: Seller::form/save/toggle
A46: 45 | B46: Penjual / Pelaku UMKM | C46: Manajemen Produk | D46: Varian & add-on dengan foto | E46: Ada | H46: Satu produk banyak pilihan | I46: Varian (selisih harga + gambar), add-on opsional. | J46: v_product_form.php
A47: 46 | B47: Penjual / Pelaku UMKM | C47: Manajemen Produk | D47: Stok produk otomatis | E47: Ada | H47: Overselling | I47: Stok dipotong saat lunas, dikembalikan saat batal. | J47: Stok_lib
A48: 47 | B48: Penjual / Pelaku UMKM | C48: Manajemen Produk | D48: Cari & urutkan produk di panel | E48: Ada | H48: Sulit mengelola katalog besar | I48: Pencarian & sortir server-side dengan paginasi. | J48: Seller::index
A49: 48 | B49: Penjual / Pelaku UMKM | C49: Manajemen Produk | D49: AI penulis deskripsi produk (dari nama + foto) | E49: Ada | F49: Ya | G49: Ya | H49: UMKM tidak pandai menulis copywriting | I49: Satu klik menghasilkan deskripsi; ada kuota pemakaian. | J49: Ai_lib::deskripsi_produk, Seller::deskripsi
A50: 49 | B50: Penjual / Pelaku UMKM | C50: Manajemen Produk | D50: Kompres/rapikan gambar otomatis | E50: Ada | H50: Foto HP berukuran besar memperlambat situs | I50: Pemrosesan gambar saat unggah. | J50: gambar_helper.php, tools/rapikan_gambar_lama.php
A51: 50 | B51: Penjual / Pelaku UMKM | C51: Manajemen Produk | D51: Tambah produk dari foto saja (AI isi nama, kategori, harga saran) | E51: Belum | G51: Ya | H51: Form panjang menakutkan | I51: Foto → draf produk lengkap, penjual tinggal konfirmasi.
A52: 51 | B52: Penjual / Pelaku UMKM | C52: Manajemen Produk | D52: Peringatan stok menipis | E52: Belum | H52: Kehabisan stok tanpa sadar | I52: Notifikasi saat stok di bawah ambang.
A53: 52 | B53: Penjual / Pelaku UMKM | C53: Manajemen Produk | D53: Unggah massal (Excel/CSV) & duplikat produk | E53: Belum | H53: Input satu per satu melelahkan | I53: Template Excel sederhana, tombol "duplikat".
A54: 53 | B54: Penjual / Pelaku UMKM | C54: Manajemen Produk | D54: Harga grosir / minimal beli bertingkat | E54: Belum | F54: Ya | H54: UMKM juga melayani reseller | I54: Harga berbeda berdasarkan jumlah.
A55: 54 | B55: Penjual / Pelaku UMKM | C55: Manajemen Produk | D55: Pengaturan pre-order per produk | E55: Belum | F55: Ya | H55: Produk dibuat sesuai pesanan | I55: Lama produksi per produk, kuota harian, DP, kalender tanggal tersedia.
A56: 55 | B56: Penjual / Pelaku UMKM | C56: Pesanan & Pengiriman | D56: Alur status pesanan satu tombol + Undo 15 menit | E56: Ada | G56: Ya | H56: Penjual gaptek takut salah klik | I56: Tombol "lanjut ke status berikutnya" dan pembatalan aksi selama 15 menit. | J56: Seller::ubah_status, undo_status, UNDO_DETIK
A57: 56 | B57: Penjual / Pelaku UMKM | C57: Pesanan & Pengiriman | D57: Antrean pesanan berprioritas | E57: Ada | H57: Pesanan penting tertimbun | I57: Pesanan lunas yang belum diproses tampil paling atas. | J57: Seller::orders
A58: 57 | B58: Penjual / Pelaku UMKM | C58: Pesanan & Pengiriman | D58: Kurir lokal / antar sendiri dengan tarif bertingkat | E58: Ada | F58: Ya | H58: Tarif ekspedisi nasional mahal untuk pengiriman dekat | I58: Penjual menetapkan ongkir sendiri per kecamatan/kota/provinsi/luar, resi opsional. | J58: Cart_lib::shipping_fee, 23_ongkir_luar.sql
A59: 58 | B59: Penjual / Pelaku UMKM | C59: Pesanan & Pengiriman | D59: Gratis ongkir minimal belanja per toko | E59: Ada | H59: Butuh pemicu pembelian lebih banyak | I59: Atur batas nominal gratis ongkir. | J59: gratis_ongkir_min
A60: 59 | B60: Penjual / Pelaku UMKM | C60: Pesanan & Pengiriman | D60: Waktu proses pesanan | E60: Ada | H60: Pembeli menuntut cepat padahal produk dibuat dulu | I60: Toko mengatur 1–30 hari waktu proses. | J60: waktu_proses_hari
A61: 60 | B61: Penjual / Pelaku UMKM | C61: Pesanan & Pengiriman | D61: Kirim foto bukti paket ke pembeli | E61: Ada | H61: Sengketa "barang tidak sesuai" | I61: Foto tersimpan di percakapan pesanan. | J61: Seller::kirim_foto
A62: 61 | B62: Penjual / Pelaku UMKM | C62: Pesanan & Pengiriman | D62: Batalkan pesanan oleh penjual | E62: Ada | H62: Stok habis/bahan tidak tersedia | I62: Pembatalan beralasan + pengembalian stok. | J62: Seller::batal_pesanan
A63: 62 | B63: Penjual / Pelaku UMKM | C63: Pesanan & Pengiriman | D63: Hubungi pembeli via WhatsApp | E63: Ada | H63: Butuh konfirmasi cepat | I63: Tautan wa.me ke nomor pembeli. | J63: seller/v_orders.php
A64: 63 | B64: Penjual / Pelaku UMKM | C64: Pesanan & Pengiriman | D64: Integrasi ekspedisi & cek resi otomatis (JNE, J&T, GoSend, Grab) | E64: Belum | H64: Penjual luar kota harus cek tarif manual | I64: Tarif real-time dan pelacakan otomatis via agregator.
A65: 64 | B65: Penjual / Pelaku UMKM | C65: Pesanan & Pengiriman | D65: Cetak label pengiriman & nota/struk | E65: Belum | G65: Ya | H65: Menulis alamat tangan memakan waktu | I65: Cetak label + invoice PDF / printer thermal.
A66: 65 | B66: Penjual / Pelaku UMKM | C66: Pesanan & Pengiriman | D66: Notifikasi pesanan baru ke WhatsApp penjual | E66: Belum | H66: Penjual tidak selalu membuka panel | I66: Pesan WA otomatis saat ada pesanan lunas.
A67: 66 | B67: Penjual / Pelaku UMKM | C67: Komunikasi & Reputasi | D67: Inbox chat pembeli | E67: Ada | H67: Pertanyaan tersebar di WA pribadi | I67: Inbox terpusat per pembeli/pesanan. | J67: Seller::pesan, chat, inbox_json
A68: 67 | B68: Penjual / Pelaku UMKM | C68: Komunikasi & Reputasi | D68: Balas ulasan | E68: Ada | H68: Ulasan buruk tidak bisa diklarifikasi | I68: Balasan publik penjual. | J68: Seller::balas, Review_model::balas
A69: 68 | B69: Penjual / Pelaku UMKM | C69: Komunikasi & Reputasi | D69: Kelola refund | E69: Ada | H69: Keluhan butuh alur jelas | I69: Setujui/tolak permintaan refund. | J69: Seller::refund, refund_putus
A70: 69 | B70: Penjual / Pelaku UMKM | C70: Komunikasi & Reputasi | D70: Balasan cepat (template chat) | E70: Belum | G70: Ya | H70: Pertanyaan berulang ("ready kak?") | I70: Template jawaban satu ketuk.
A71: 70 | B71: Penjual / Pelaku UMKM | C71: Keuangan & Naik Kelas (Pembeda Utama) | D71: Ringkasan pendapatan & status dana | E71: Ada | H71: Penjual tidak tahu uangnya di mana | I71: Dana tertahan / siap cair / sudah cair, potongan komisi tercatat. | J71: Seller::pendapatan, Pendapatan_lib
A72: 71 | B72: Penjual / Pelaku UMKM | C72: Keuangan & Naik Kelas (Pembeda Utama) | D72: Pembukuan sederhana (kas masuk-keluar) | E72: Belum | F72: Ya | G72: Ya | H72: Mayoritas UMKM tidak mencatat keuangan sehingga sulit akses modal | I72: Penjualan marketplace tercatat otomatis, penjual menambah pengeluaran (bahan, sewa) dengan tombol besar, laporan laba sederhana harian/bulanan.
A73: 72 | B73: Penjual / Pelaku UMKM | C73: Keuangan & Naik Kelas (Pembeda Utama) | D73: Penjualan offline / kasir mini (POS) | E73: Belum | F73: Ya | H73: UMKM juga berjualan di warung/pasar, data terpisah | I73: Catat penjualan langsung, stok tersinkron.
A74: 73 | B74: Penjual / Pelaku UMKM | C74: Keuangan & Naik Kelas (Pembeda Utama) | D74: Laporan penjualan & statistik toko | E74: Belum | H74: Tidak tahu produk mana yang laku | I74: Grafik omzet, produk terlaris, jam ramai; ekspor Excel/PDF.
A75: 74 | B75: Penjual / Pelaku UMKM | C75: Keuangan & Naik Kelas (Pembeda Utama) | D75: Laporan keuangan siap ajukan KUR/pinjaman | E75: Belum | F75: Ya | H75: Bank meminta laporan keuangan | I75: Ekspor laporan rapi dari data pembukuan.
A76: 75 | B76: Penjual / Pelaku UMKM | C76: Keuangan & Naik Kelas (Pembeda Utama) | D76: Voucher & promo toko | E76: Belum | H76: Sulit bersaing harga | I76: Diskon persentase/nominal, voucher pelanggan setia.
A77: 76 | B77: Penjual / Pelaku UMKM | C77: Keuangan & Naik Kelas (Pembeda Utama) | D77: Akademi UMKM (pelatihan & pendampingan) | E77: Belum | F77: Ya | H77: UMKM tidak tahu cara foto produk, menentukan harga, atau pemasaran | I77: Modul video pendek, kuis, sertifikat, jadwal konsultasi dengan pendamping/mentor.
A78: 77 | B78: Penjual / Pelaku UMKM | C78: Keuangan & Naik Kelas (Pembeda Utama) | D78: Skor "Naik Kelas" toko | E78: Belum | F78: Ya | H78: Tidak ada arah pengembangan usaha | I78: Level toko (Pemula → Berkembang → Unggul) berdasarkan kelengkapan profil, legalitas, kecepatan respons, rating, dengan saran langkah berikutnya.
A79: 78 | B79: Penjual / Pelaku UMKM | C79: Keuangan & Naik Kelas (Pembeda Utama) | D79: QR code / kartu nama toko digital | E79: Belum | H79: Promosi offline sulit diarahkan ke toko online | I79: QR siap cetak menuju halaman toko.
A80: 79 | B80: Admin / Pengelola Platform | C80: Monitoring | D80: Dashboard ringkasan | E80: Ada | H80: Admin butuh gambaran cepat | I80: Toko aktif/menunggu, produk aktif, akun, pesanan perlu diproses, pesanan hari ini, omzet bulan berjalan. | J80: admin/Dashboard.php
A81: 80 | B81: Admin / Pengelola Platform | C81: Monitoring | D81: Laporan & analitik platform | E81: Belum | H81: Tidak bisa mengukur pertumbuhan | I81: GMV per periode/wilayah/kategori, pertumbuhan toko, ekspor data.
A82: 81 | B82: Admin / Pengelola Platform | C82: Monitoring | D82: Peta sebaran UMKM | E82: Belum | F82: Ya | H82: Pemda/mitra ingin tahu wilayah yang perlu dibina | I82: Peta toko per kecamatan beserta tingkat aktivitasnya.
A83: 82 | B83: Admin / Pengelola Platform | C83: Pengguna & Toko | D83: Persetujuan & kelola toko | E83: Ada | H83: Mencegah toko fiktif | I83: Daftar toko menunggu, ubah data, aktif/nonaktifkan. | J83: admin/Stores.php
A84: 83 | B84: Admin / Pengelola Platform | C84: Pengguna & Toko | D84: Kelola pengguna | E84: Ada | H84: Akun bermasalah | I84: Aktif/nonaktif, ubah peran, reset sandi. | J84: admin/Users.php
A85: 84 | B85: Admin / Pengelola Platform | C85: Pengguna & Toko | D85: Verifikasi dokumen (KTP/NIB/Halal) & lencana | E85: Belum | H85: Kepercayaan pembeli | I85: Antrean verifikasi dokumen, pemberian lencana.
A86: 85 | B86: Admin / Pengelola Platform | C86: Pengguna & Toko | D86: Manajemen pendamping UMKM | E86: Belum | F86: Ya | H86: Pembinaan tidak terpantau | I86: Tetapkan pendamping per toko, catatan kunjungan, progres "naik kelas".
A87: 86 | B87: Admin / Pengelola Platform | C87: Katalog & Konten | D87: Kelola kategori + ikon | E87: Ada | H87: Kategori berantakan | I87: Tambah/ubah/nonaktifkan/hapus kategori aman. | J87: admin/Categories.php
A88: 87 | B88: Admin / Pengelola Platform | C88: Katalog & Konten | D88: Moderasi produk | E88: Belum | H88: Produk terlarang/menyesatkan lolos | I88: Daftar produk semua toko, takedown, laporan pengguna.
A89: 88 | B89: Admin / Pengelola Platform | C89: Katalog & Konten | D89: CMS banner & halaman promo | E89: Belum | H89: Kampanye musiman perlu deploy kode | I89: Atur banner beranda, halaman kampanye ("Pekan Produk Lokal").
A90: 89 | B90: Admin / Pengelola Platform | C90: Katalog & Konten | D90: Kelola konten Akademi UMKM | E90: Belum | H90: Materi pelatihan perlu diperbarui | I90: Unggah modul, kuis, jadwal webinar.
A91: 90 | B91: Admin / Pengelola Platform | C91: Katalog & Konten | D91: Moderasi ulasan & laporan | E91: Belum | H91: Ulasan kasar/spam | I91: Sembunyikan ulasan, tangani laporan.
A92: 91 | B92: Admin / Pengelola Platform | C92: Transaksi & Keuangan | D92: Pencairan dana ke toko | E92: Ada | H92: Penjual menunggu uang | I92: Cairkan, tandai selesai/gagal dengan bukti. | J92: admin/Keuangan.php, Pendapatan_lib
A93: 92 | B93: Admin / Pengelola Platform | C93: Transaksi & Keuangan | D93: Komisi platform terkunci per pesanan | E93: Ada | H93: Perubahan komisi merusak catatan lama | I93: Komisi dihitung & disimpan saat lunas, dibatasi 0–50%. | J93: Pendapatan_lib::catat
A94: 93 | B94: Admin / Pengelola Platform | C94: Transaksi & Keuangan | D94: Proses refund | E94: Ada | H94: Gateway tidak punya API refund | I94: Admin menandai refund yang disetujui penjual sebagai selesai. | J94: Keuangan::refund, refund_selesai
A95: 94 | B95: Admin / Pengelola Platform | C95: Transaksi & Keuangan | D95: Rekonsiliasi pembayaran otomatis | E95: Ada | H95: Pesanan menggantung/tidak terbayar | I95: Callback Duitku tercatat, sapu otomatis pesanan kedaluwarsa. | J95: Payment::callback/sweep, Order_model::log_callback, tandai_kedaluwarsa
A96: 95 | B96: Admin / Pengelola Platform | C96: Transaksi & Keuangan | D96: Pusat sengketa (dispute) | E96: Belum | H96: Pembeli dan penjual tidak sepakat soal refund | I96: Admin menengahi dengan bukti chat & foto.
A97: 96 | B97: Admin / Pengelola Platform | C97: Transaksi & Keuangan | D97: Voucher & subsidi ongkir platform | E97: Belum | H97: Butuh program akuisisi pembeli | I97: Buat voucher platform dengan kuota & anggaran.
A98: 97 | B98: Admin / Pengelola Platform | C98: Transaksi & Keuangan | D98: Pengaturan sistem lewat UI | E98: Belum | H98: Komisi, kunci API, kontak WA admin diubah lewat file config | I98: Halaman pengaturan.
A99: 98 | B99: Admin / Pengelola Platform | C99: Komunikasi & Keamanan | D99: Broadcast pengumuman ke penjual (web + WA) | E99: Belum | H99: Info pelatihan/kebijakan tidak sampai | I99: Kirim pengumuman tersegmentasi per wilayah/kategori.
A100: 99 | B100: Admin / Pengelola Platform | C100: Komunikasi & Keamanan | D100: Log audit aktivitas admin | E100: Belum | H100: Tidak bisa melacak siapa mengubah apa | I100: Riwayat aksi admin. | J100: Repo baru punya log status pesanan & callback
...

Sheet Roadmap
A1: Tahap | B1: Fitur yang Direkomendasikan
A2: Quick win (1–2 sprint) | B2: notifikasi WhatsApp (pembeli & penjual), lupa sandi mandiri, tombol share WA (kodenya sudah ada, tinggal diaktifkan), peringatan stok menipis, mode libur toko, template balasan chat.
A3: Pembeda utama (2–4 sprint) | B3: pembukuan sederhana + laporan penjualan, pre-order fleksibel per produk (DP & kalender), COD dengan batas nominal, pickup di toko.
A4: Naik kelas (jangka menengah) | B4: Akademi UMKM, skor "Naik Kelas", bantuan legalitas + lencana verifikasi, laporan siap KUR, manajemen pendamping.
A5: Skala (jangka panjang) | B5: integrasi agregator ekspedisi, checkout multi-toko, voucher platform, POS offline, PWA.
